runml/__init__.py
runml/__main__.py
runml/_config.py
runml/_version.py
runml/analyzers/__init__.py
runml/analyzers/base_analyzer.py
runml/analyzers/cat_target_drift_analyzer.py
runml/analyzers/classification_performance_analyzer.py
runml/analyzers/data_drift_analyzer.py
runml/analyzers/data_quality_analyzer.py
runml/analyzers/num_target_drift_analyzer.py
runml/analyzers/prob_classification_performance_analyzer.py
runml/analyzers/regression_performance_analyzer.py
runml/analyzers/utils.py
runml/analyzers/stattests/__init__.py
runml/analyzers/stattests/chisquare_stattest.py
runml/analyzers/stattests/ks_stattest.py
runml/analyzers/stattests/z_stattest.py
runml/dashboard/__init__.py
runml/dashboard/dashboard.py
runml/dashboard/tabs/__init__.py
runml/dashboard/tabs/base_tab.py
runml/dashboard/tabs/cat_target_drift_tab.py
runml/dashboard/tabs/classification_performance_tab.py
runml/dashboard/tabs/data_drift_tab.py
runml/dashboard/tabs/data_quality_tab.py
runml/dashboard/tabs/num_target_drift_tab.py
runml/dashboard/tabs/prob_classification_performance_tab.py
runml/dashboard/tabs/regression_performance_tab.py
runml/dashboard/tabs/widget_gallery_tab.py
runml/dashboard/widgets/__init__.py
runml/dashboard/widgets/bar_widget.py
runml/dashboard/widgets/cat_output_drift_widget.py
runml/dashboard/widgets/cat_target_pred_feature_table_widget.py
runml/dashboard/widgets/class_conf_matrix_widget.py
runml/dashboard/widgets/class_confusion_based_feature_distr_table_widget.py
runml/dashboard/widgets/class_metrics_matrix_widget.py
runml/dashboard/widgets/class_quality_metrics_bar_widget.py
runml/dashboard/widgets/class_support_widget.py
runml/dashboard/widgets/class_target_name_widget.py
runml/dashboard/widgets/counter_widget.py
runml/dashboard/widgets/data_drift_table_widget.py
runml/dashboard/widgets/data_quality_correlations.py
runml/dashboard/widgets/data_quality_features_widget.py
runml/dashboard/widgets/data_quality_summary.py
runml/dashboard/widgets/expandable_list_widget.py
runml-0.1.47.dev0.dist-info/LICENSE
runml-0.1.47.dev0.dist-info/METADATA
runml-0.1.47.dev0.dist-info/WHEEL
runml-0.1.47.dev0.dist-info/top_level.txt
runml-0.1.47.dev0.dist-info/RECORD
