Metadata-Version: 2.1
Name: runml
Version: 0.1.47.dev0
Summary: Open-source tools to analyze, monitor, and debug machine learning model in production.
Home-page: https://github.com/runmlai/runml
Author: Emeli Dral
Author-email: emeli.dral@gmail.com
License: UNKNOWN
Platform: Linux
Platform: Mac OS X
Platform: Windows
Requires-Python: >=3.6
License-File: LICENSE
Requires-Dist: dataclasses (>=0.6)
Requires-Dist: plotly (>=5.5.0)
Requires-Dist: statsmodels (>=0.12.2)
Requires-Dist: scikit-learn (>=0.23.2)
Requires-Dist: pandas (>=1.1.5)
Requires-Dist: numpy (>=1.19.5)
Requires-Dist: scipy (>=1.5.4)
Requires-Dist: requests (>=2.19.0)
Requires-Dist: PyYAML (~=5.1)
Provides-Extra: dev
Requires-Dist: setuptools (==50.3.2) ; extra == 'dev'
Requires-Dist: flake8 (==4.0.1) ; extra == 'dev'
Requires-Dist: jupyter (==1.0.0) ; extra == 'dev'
Requires-Dist: mypy (==0.910) ; extra == 'dev'
Requires-Dist: pytest (==6.2.5) ; extra == 'dev'
Requires-Dist: types-PyYAML (==6.0.1) ; extra == 'dev'
Requires-Dist: types-requests (==2.26.0) ; extra == 'dev'
